./LICENSE
./PKG-INFO
./README.md
./__init__.py
./openapi.json
./pyproject.toml
./server.py
bach_ai_content_detector_ai_gpt-1.0.0.dist-info/METADATA
bach_ai_content_detector_ai_gpt-1.0.0.dist-info/WHEEL
bach_ai_content_detector_ai_gpt-1.0.0.dist-info/entry_points.txt
bach_ai_content_detector_ai_gpt-1.0.0.dist-info/licenses/LICENSE
bach_ai_content_detector_ai_gpt-1.0.0.dist-info/RECORD
